AUTHORS
MANIFEST.in
README.rst
setup.py
apicapi/__init__.py
apicapi/apic_client.py
apicapi/apic_domain.py
apicapi/apic_manager.py
apicapi/apic_mapper.py
apicapi/config.py
apicapi/exceptions.py
apicapi.egg-info/PKG-INFO
apicapi.egg-info/SOURCES.txt
apicapi.egg-info/dependency_links.txt
apicapi.egg-info/entry_points.txt
apicapi.egg-info/not-zip-safe
apicapi.egg-info/top_level.txt
apicapi/db/__init__.py
apicapi/db/noop_manager.py
apicapi/tools/__init__.py
apicapi/tools/bondwatch.py
apicapi/tools/cleanup.py
apicapi/tools/host_report.py
apicapi/tools/reflector.py
apicapi/tools/cli/__init__.py
apicapi/tools/cli/common.py
apicapi/tools/cli/shell.py
apicapi/tools/cli/neutron/__init__.py
apicapi/tools/cli/neutron/client.py
debian/.gitignore
debian/build-deb.sh
debian/changelog.in
debian/compat
debian/control
debian/copyright
debian/install
debian/rules
debian/source/format
etc/apic.bash_completion
etc/conf_sample.ini
rpm/apicapi.spec.in
rpm/build-rpm.sh