Metadata-Version: 1.0
Name: apicapi
Version: 1.0.14
Summary: This library provides an interface to the APIC REST api.
Home-page: http://github.com/noironetworks/apicapi/
Author: Cisco Systems, Inc.
Author-email: apicapi@noironetworks.com
License: http://www.apache.org/licenses/LICENSE-2.0
Platform: UNKNOWN
